{
  "name": "Groupon",
  "namespace": "Groupon",
  "serviceProvider": "Groupon\\Providers\\GroupOnServiceProvider",
  "marketplaceName"   : {"de":"German display name of plugin","en":"English display name of plugin"},
  "description": "GroupON plugin for Plenty Market 7",
  "shortDescription"  : {"de":"German short description","en":"English short description"},
  "keywords":["terra","backend", "Groupon","integration"],
  "categories": ["3523", "3521"],
  "isClosedSource":true,
  "type": "backend",
  "license":"MIT",
  "version":"0.0.1",
  "price":0.00,
  "pluginIcon":"groupon_xs.png",
  "author": "hashtages",
  "authorIcon":"hashtages_xs.png"
  "email": "hello@hashtages.com",
  "phone": "+49 (0) 4264-776949-5",
}
